freealg/__init__.py
freealg/__version__.py
freealg/_util.py
freealg/_algebraic_form/__init__.py
freealg/_algebraic_form/_branch_points.py
freealg/_algebraic_form/_constraints.py
freealg/_algebraic_form/_continuation_algebraic.py
freealg/_algebraic_form/_cusp.py
freealg/_algebraic_form/_cusp_wrap.py
freealg/_algebraic_form/_decompress.py
freealg/_algebraic_form/_decompress2.py
freealg/_algebraic_form/_decompress4.py
freealg/_algebraic_form/_decompress5.py
freealg/_algebraic_form/_decompress6.py
freealg/_algebraic_form/_decompress7.py
freealg/_algebraic_form/_decompress8.py
freealg/_algebraic_form/_decompress9.py
freealg/_algebraic_form/_decompress_new.py
freealg/_algebraic_form/_decompress_new_2.py
freealg/_algebraic_form/_decompress_util.py
freealg/_algebraic_form/_edge.py
freealg/_algebraic_form/_homotopy.py
freealg/_algebraic_form/_homotopy2.py
freealg/_algebraic_form/_homotopy3.py
freealg/_algebraic_form/_homotopy4.py
freealg/_algebraic_form/_homotopy5.py
freealg/_algebraic_form/_moments.py
freealg/_algebraic_form/_sheets_util.py
freealg/_algebraic_form/_support.py
freealg/_algebraic_form/algebraic_form.py
freealg/_free_form/__init__.py
freealg/_free_form/_chebyshev.py
freealg/_free_form/_damp.py
freealg/_free_form/_decompress.py
freealg/_free_form/_density_util.py
freealg/_free_form/_jacobi.py
freealg/_free_form/_linalg.py
freealg/_free_form/_pade.py
freealg/_free_form/_plot_util.py
freealg/_free_form/_sample.py
freealg/_free_form/_series.py
freealg/_free_form/_support.py
freealg/_free_form/free_form.py
freealg/_geometric_form/__init__.py
freealg/_geometric_form/_continuation_genus0.py
freealg/_geometric_form/_continuation_genus1.py
freealg/_geometric_form/_elliptic_functions.py
freealg/_geometric_form/_sphere_maps.py
freealg/_geometric_form/_torus_maps.py
freealg/_geometric_form/geometric_form.py
freealg/distributions/__init__.py
freealg/distributions/_chiral_block.py
freealg/distributions/_compound_poisson.py
freealg-0.7.17.dist-info/licenses/AUTHORS.txt
freealg-0.7.17.dist-info/licenses/LICENSE.txt
freealg-0.7.17.dist-info/METADATA
freealg-0.7.17.dist-info/WHEEL
freealg-0.7.17.dist-info/top_level.txt
freealg-0.7.17.dist-info/RECORD
