Metadata-Version: 2.4
Name: freealg
Version: 0.7.17
Summary: Free probability for large matrices
Home-page: https://github.com/ameli/freealg
Download-URL: https://github.com/ameli/freealg/archive/main.zip
Project-URL: Documentation, https://ameli.github.io/freealg
Project-URL: Source, https://github.com/ameli/freealg
Project-URL: Tracker, https://github.com/ameli/freealg/issues
Keywords: linalg,free-probability
Platform: Linux
Platform: OSX
Platform: Windows
Classifier: Programming Language :: Python
Classifier: Programming Language :: Python :: 3.9
Classifier: Programming Language :: Python :: 3.10
Classifier: Programming Language :: Python :: 3.11
Classifier: Programming Language :: Python :: 3.12
Classifier: Programming Language :: Python :: Implementation :: CPython
Classifier: License :: OSI Approved :: BSD License
Classifier: Operating System :: POSIX :: Linux
Classifier: Operating System :: Microsoft :: Windows
Classifier: Operating System :: MacOS
Classifier: Natural Language :: English
Classifier: Intended Audience :: Science/Research
Classifier: Intended Audience :: Developers
Classifier: Topic :: Software Development
Classifier: Topic :: Software Development :: Libraries :: Python Modules
Requires-Python: >=3.10
License-File: LICENSE.txt
License-File: AUTHORS.txt
Requires-Dist: numpy
Requires-Dist: scipy
Requires-Dist: texplot
Requires-Dist: matplotlib
Requires-Dist: colorcet
Requires-Dist: statsmodels
Requires-Dist: numba
Requires-Dist: tqdm
Provides-Extra: test
Provides-Extra: docs
Dynamic: classifier
Dynamic: description
Dynamic: description-content-type
Dynamic: download-url
Dynamic: home-page
Dynamic: keywords
Dynamic: license-file
Dynamic: platform
Dynamic: project-url
Dynamic: provides-extra
Dynamic: requires-dist
Dynamic: requires-python
Dynamic: summary
